tools_09d3/__init__.py
tools_09d3/impl.py
tools_09d3-0.0.3.dist-info/LICENSE
tools_09d3-0.0.3.dist-info/METADATA
tools_09d3-0.0.3.dist-info/WHEEL
tools_09d3-0.0.3.dist-info/entry_points.txt
tools_09d3-0.0.3.dist-info/top_level.txt
tools_09d3-0.0.3.dist-info/RECORD
