Metadata-Version: 2.1
Name: tools-09d3
Version: 0.0.3
Summary: A small example package
Home-page: https://github.com/phfrohring/python
Author: Pierre-Henry Fröhring
Author-email: contact@phfrohring.com
License: UNKNOWN
Project-URL: Bug Tracker, https://github.com/phfrohring/python/issues
Platform: UNKNOWN
Classifier: Programming Language :: Python :: 3
Classifier: License :: OSI Approved :: MIT License
Classifier: Operating System :: OS Independent
Requires-Python: >=3.6
Provides-Extra: dev
Requires-Dist: pytest ; extra == 'dev'
Requires-Dist: sphinx ; extra == 'dev'
Requires-Dist: black ; extra == 'dev'
Requires-Dist: isort ; extra == 'dev'
Requires-Dist: sphinx-rtd-theme ; extra == 'dev'
Requires-Dist: numpydoc ; extra == 'dev'
Requires-Dist: build ; extra == 'dev'
Requires-Dist: twine ; extra == 'dev'
